Metadata-Version: 2.1
Name: pydemonstrativo
Version: 0.0.1
Summary: Demonstrativos Financeiros - Dados CVM
Home-page: https://github.com/andremsilveira/pydemonstrativos
Author: Andre Silveira
Author-email: martinslucianofigueira@gmail.com
License: MIT License
Keywords: Pacote
Platform: UNKNOWN
